delightful/__init__.py
delightful-0.0.1.dev0.dist-info/LICENSE
delightful-0.0.1.dev0.dist-info/WHEEL
delightful-0.0.1.dev0.dist-info/METADATA
delightful-0.0.1.dev0.dist-info/RECORD
